coeur/__init__.py
coeur/__main__.py
coeur/apps/cmp/cmp.py
coeur/apps/cmp/engine.py
coeur/apps/pds/channels.py
coeur/apps/pds/engine.py
coeur/apps/pds/pds.py
coeur/apps/ssg/admin.py
coeur/apps/ssg/bootstrap.py
coeur/apps/ssg/build.py
coeur/apps/ssg/db.py
coeur/apps/ssg/markdown.py
coeur/apps/ssg/ssg.py
coeur/apps/ssg/templates/base.html
coeur/apps/ssg/templates/footer.html
coeur/apps/ssg/templates/header.html
coeur/apps/ssg/templates/page-item.html
coeur/apps/ssg/templates/page-navigation.html
coeur/apps/ssg/templates/page.html
coeur/apps/ssg/templates/post.html
coeur/apps/ssg/templates/sitemap.xml
coeur/apps/ssg/templates/static/css/style.css
coeur/apps/ssg/templates/static/img/default-blog-cover.jpg
coeur/apps/ssg/templates/static/img/favicon.ico
coeur/apps/ssg/templates/static/img/sacre-coeur.png
coeur/apps/ssg/templates/static/js/logic.js
coeur/main.py
coeur/utils.py
blog_coeur-0.0.18.dist-info/METADATA
blog_coeur-0.0.18.dist-info/WHEEL
blog_coeur-0.0.18.dist-info/entry_points.txt
blog_coeur-0.0.18.dist-info/RECORD
