Metadata-Version: 2.1
Name: blog-coeur
Version: 0.0.18
Summary: Coeur - static site management
Home-page: https://github.com/sr2ds/coeur
Author: David Silva
Author-email: srdavidsilva@gmail.com
Requires-Python: >=3.10,<3.14
Classifier: Programming Language :: Python :: 3
Classifier: Programming Language :: Python :: 3.10
Classifier: Programming Language :: Python :: 3.11
Classifier: Programming Language :: Python :: 3.12
Requires-Dist: atproto (>=0.0.55,<0.0.56)
Requires-Dist: beautifulsoup4 (>=4.12.3,<5.0.0)
Requires-Dist: fastapi (>=0.115.5,<0.116.0)
Requires-Dist: instagrapi (>=2.1.2,<3.0.0)
Requires-Dist: jinja2 (>=3.1.4,<4.0.0)
Requires-Dist: lxml (>=5.3.0,<6.0.0)
Requires-Dist: minify-html (>=0.15.0,<0.16.0)
Requires-Dist: mistune (>=3.0.2,<4.0.0)
Requires-Dist: openai (>=1.51.2,<2.0.0)
Requires-Dist: pillow (>=11.0.0,<12.0.0)
Requires-Dist: psutil (>=5.9.8,<6.0.0)
Requires-Dist: python-dotenv (>=1.0.1,<2.0.0)
Requires-Dist: python-slugify (>=8.0.4,<9.0.0)
Requires-Dist: pyyaml (>=6.0.1,<7.0.0)
Requires-Dist: sqladmin (>=0.20.1,<0.21.0)
Requires-Dist: sqlalchemy (>=2.0.30,<3.0.0)
Requires-Dist: toml (>=0.10.2,<0.11.0)
Requires-Dist: typer[all] (>=0.12.3,<0.13.0)
Requires-Dist: uvicorn (>=0.32.0,<0.33.0)
Requires-Dist: watchdog (>=4.0.1,<5.0.0)
Project-URL: Repository, https://github.com/sr2ds/coeur
